Workbook

Sheet Hist
A1: Year | B1: Revenue | C1: Cost of Revenue | D1: Operating Ex | E1: Depreciation | F1: Capex | G1: Accounts Rec | H1: Iventory | I1: other CA | J1: OP CA | K1: Accounts Payable | L1: Accurred expense | M1: Current provisions | N1: Other CL | O1: OP CL | P1: Tax Provision | Q1: Income before tax | R1: Short Term debt | S1: Long term debt | T1: Capital leases C | U1: Capital leases L | V1: Interest expense | W1: Cash - Short term investments
A2: 2021 | B2: 53823000 | C2: 40217000 | D2: 7110000 | E2: 2911000 | F2: 8014000
A3: 2022 | B3: 81462000 | C3: 60609000 | D3: 7021000 | E3: 3747000 | F3: 7172000
A4: 2023 | B4: 96773000 | C4: 79113000 | D4: 8769000 | E4: 4667000 | F4: 8899000 | G4: 3508000 | H4: 13626000 | I4: 3388000 | J4: =SUM(G4+H4+I4) -> 20522000 | K4: 14431000 | L4: 4046000 | M4: 1765000 | N4: 517000 | O4: =SUM(K4:N4) -> 20759000 | P4: -5001000 | Q4: 9973000 | R4: 1975000 | S4: 2682000 | T4: 1070000 | U4: 3846000 | V4: 156000 | W4: 29094000
A6: COGS % of Revenue | B6: =C4/B4 -> 0.81751108
A7: OpEx% of Revenue | B7: =D4/B4 -> 0.090614118
A8: Depreciation% of Rev | B8: =E4/B4 -> 0.048226261
A9: Capex% of Rev | B9: =F4/B4 -> 0.091957467
A10: OP NWC | B10: =J4-O4 -> -237000
A11: NWC% of WC | B11: =B10/B4 -> -0.0024490302
A12: Rev Grwoth 22-23 | B12: =(B4-B3)/B3 -> 0.18795267
A13: Rev Grwoth 21-22 | B13: =(B3-B2)/B2 -> 0.51351653
A14: Avg Historical Growth | B14: =AVERAGE(B12:B13) -> 0.3507346
A15: EAR | B15: 0.1

Sheet Assumptions
A1: Assumptions
A2: Base year Rev | B2: =Hist!B4 -> 96773000
A3: COGS % | B3: =Hist!B6 -> 0.81751108
A4: OpEx % | B4: =Hist!B7 -> 0.090614118
A5: Dep % | B5: =Hist!B8 -> 0.048226261
A6: Capex% | B6: =Hist!B9 -> 0.091957467
A7: OP NWC % | B7: =Hist!B11 -> -0.0024490302
A8: Avg Historical Growth | B8: =Hist!B14 -> 0.3507346
A9: Tax rate | B9: =Hist!B15 -> 0.1
A10: GR | B10: 0.025

Sheet FCF
B1: Year 1 | C1: Year 2 | D1: Year 3 | E1: Year 4 | F1: Year 5
A2: NOPAT | B2: =Forecast!B8 -> 10808443 | C2: =Forecast!C8 -> 14599338 | D2: =Forecast!D8 -> 19719831 | E2: =Forecast!E8 -> 26636258 | F2: =Forecast!F8 -> 35978515
A3: Depreciation | B3: =Forecast!B2*Assumptions!B5 -> 6303878.4 | C3: =Forecast!C2*Assumptions!B5 -> 8514866.6 | D3: =Forecast!D2*Assumptions!B5 -> 11501325 | E3: =Forecast!E2*Assumptions!B5 -> 15535237 | F3: =Forecast!F2*Assumptions!B5 -> 20983983
A4: CapEx | B4: =Forecast!B2*Assumptions!B6 -> 12020187 | C4: =Forecast!C2*Assumptions!B6 -> 16236083 | D4: =Forecast!D2*Assumptions!B6 -> 21930639 | E4: =Forecast!E2*Assumptions!B6 -> 29622472 | F4: =Forecast!F2*Assumptions!B6 -> 40012098
A5: NWC | B5: =Forecast!B2*Assumptions!B7 -> -320124.1 | C5: =Forecast!C2*Assumptions!B7 -> -432402.7 | D5: =Forecast!D2*Assumptions!B7 -> -584061.28 | E5: =Forecast!E2*Assumptions!B7 -> -788911.78 | F5: =Forecast!F2*Assumptions!B7 -> -1065610.4
A6: ΔNWC | B6: 0 | C6: =C5-B5 -> -112278.6 | D6: =D5-C5 -> -151658.58 | E6: =E5-D5 -> -204850.5 | F6: =F5-E5 -> -276698.65
A7: Free Cash Flow | B7: =B2+B3-B4-B6 -> 5092134.4 | C7: =C2+C3-C4-C6 -> 6990400.6 | D7: =D2+D3-D4-D6 -> 9442176 | E7: =E2+E3-E4-E6 -> 12753874 | F7: =F2+F3-F4-F6 -> 17227098

Sheet DCF Valuation
B1: Year 1 | C1: Year 2 | D1: Year 3 | E1: Year 4 | F1: Year 5
A2: FCF | B2: =FCF!B7 -> 5092134.4 | C2: =FCF!C7 -> 6990400.6 | D2: =FCF!D7 -> 9442176 | E2: =FCF!E7 -> 12753874 | F2: =FCF!F7 -> 17227098
A3: Discount factor | B3: =1/(1+DCF!B11)^1 -> 0.86662694 | C3: =1/(1+DCF!B11)^2 -> 0.75104226 | D3: =1/(1+DCF!B11)^3 -> 0.65087345 | E3: =1/(1+DCF!B11)^4 -> 0.56406447 | F3: =1/(1+DCF!B11)^5 -> 0.48883347
A4: PV of FCF | B4: =B2*B3 -> 4412980.8 | C4: =C2*C3 -> 5250086.3 | D4: =D2*D3 -> 6145661.7 | E4: =E2*E3 -> 7194007 | F4: =F2*F3 -> 8421182.3
A5: Terminal Value | F5: =(FCF!F7 * (1 + Assumptions!B10)) / (DCF!B11 - Assumptions!B10) -> 1.3698919e+08
A6: PV of Terminal Value | F6: ='DCF Valuation'!F5*'DCF Valuation'!F3 -> 66964902
A7: Sum of PV of FCF | B7: =SUM(B4:F4) -> 31423918
A8: Enterprise Value | B8: =B7+F6 -> 98388820
A9: Equity Value | B9: =B8+Hist!W4-DCF!E2 -> 1.1790982e+08
A10: Intrinsic Value per share | B10: =B9/DCF!G2 -> 0.035408354

Sheet Forecast
B1: Year 1 | C1: Year 2 | D1: Year 3 | E1: Year 4 | F1: Year 5
A2: Revenue | B2: =Assumptions!B2*(1+Assumptions!B8) -> 1.3071464e+08 | C2: =B2*(1+Assumptions!B8) -> 1.7656079e+08 | D2: =C2*(1+Assumptions!B8) -> 2.3848676e+08 | E2: =D2*(1+Assumptions!B8) -> 3.2213232e+08 | F2: =E2*(1+Assumptions!B8) -> 4.3511527e+08
A3: COGS | B3: =B2*Assumptions!B3 -> 1.0686067e+08 | C3: =C2*Assumptions!B3 -> 1.443404e+08 | D3: =D2*Assumptions!B3 -> 1.9496557e+08 | E3: =E2*Assumptions!B3 -> 2.6334674e+08 | F3: =F2*Assumptions!B3 -> 3.5571155e+08
A4: Gross Profit | B4: =B2-B3 -> 23853973 | C4: =C2-C3 -> 32220387 | D4: =D2-D3 -> 43521191 | E4: =E2-E3 -> 58785578 | F4: =F2-F3 -> 79403714
A5: OpEx | B5: =B2*Assumptions!B4 -> 11844592 | C5: =C2*Assumptions!B4 -> 15998900 | D5: =D2*Assumptions!B4 -> 21610267 | E5: =E2*Assumptions!B4 -> 29189736 | F5: =F2*Assumptions!B4 -> 39427586
A6: EBIT | B6: =B4-B5 -> 12009381 | C6: =C4-C5 -> 16221487 | D6: =D4-D5 -> 21910923 | E6: =E4-E5 -> 29595842 | F6: =F4-F5 -> 39976128
A7: Taxes | B7: =B6*Assumptions!B9 -> 1200938.1 | C7: =C6*Assumptions!B9 -> 1622148.7 | D7: =D6*Assumptions!B9 -> 2191092.3 | E7: =E6*Assumptions!B9 -> 2959584.2 | F7: =F6*Assumptions!B9 -> 3997612.8
A8: NOPAT | B8: =B6-B7 -> 10808443 | C8: =C6-C7 -> 14599338 | D8: =D6-D7 -> 19719831 | E8: =E6-E7 -> 26636258 | F8: =F6-F7 -> 35978515

Sheet DCF
A1: Risk free rate % | B1: Market Risk Premium % | C1: Beta | D1: Interest Expense | E1: Total Debt | F1: Tax Rate | G1: Shares outstanding | H1: Price
A2: 0.045 | B2: 0.055 | C2: 1.98 | D2: =Hist!V4 -> 156000 | E2: =Hist!R4+Hist!S4+Hist!T4+Hist!U4 -> 9573000 | F2: =Assumptions!B9 -> 0.1 | G2: 3330000000 | H2: 418.93
A4: CAPM (RE) | B4: =A2+C2*B2 -> 0.1539
A5: Pre tax (rd) | B5: =D2/E2 -> 0.016295832
A6: After tax (rd) | B6: =B5*(1-F2) -> 0.014666249
A7: Equity value | B7: =G2*H2 -> 1395036900000
A8: Total capital | B8: =B7+E2 -> 1395046473000
A9: Equity weight | B9: =B7/B8 -> 0.99999314
A10: Weight Debt | B10: =E2/B8 -> 6.862137e-06
A11: WACC | B11: =B9*B4+B10*B6 -> 0.15389904

Sheet Valuation Summary
B1: PV of FCFs | C1: PV of Terminal Value | D1: Cash | E1: Debt | F1: Equity Value
A2: Value | B2: 31423918 | C2: 66964902 | D2: 29094000 | E2: -9573000 | F2: 117909820
A24: TESLA 5 YEAR DCF VALUATION SUMMARY OVERVIEW
A26: This project develops a fully linked 5-year discounted cash flow (DCF) valuation model for Tesla using real historical financial data and professionally structured assumptions. The model includes integrated forecasting, unlevered free cash flow modeling, WACC estimation, terminal value calculation, and full enterprise-to-equity value reconciliation.
A31: Key Assumptions Revenue growth based on Tesla’s 2021–2023 historical trend COGS, OpEx, depreciation, and CapEx modeled as % of revenue Effective tax rate: 10% Net working capital modeled at 22% of revenue Terminal growth rate (g): 2.5% WACC (discount rate): 15.39% Shares outstanding: 3.33B
A40: Free Cash Flow Forecast Unlevered free cash flow grows from $5.09M in Year 1 to $17.23M in Year 5, reflecting scalable operating performance and consistent reinvestment behavior.
A44: DCF Valuation Results PV of Free Cash Flows (Years 1–5): $31.42M PV of Terminal Value: $66.96M Enterprise Value: $98.39M Cash & Short-term investments: $29.09M Total debt: $9.57M Equity Value: $117.91M Intrinsic Value per Share: $0.035
A53: Interpretation of Results This valuation demonstrates a complete and technically accurate application of the DCF framework. The model clearly shows how revenue growth, operating efficiency, reinvestment levels, and discount rates shape intrinsic value, providing insight into Tesla’s long-term financial drivers. While the inputs reflect a conservative baseline scenario, the analysis showcases strong skills in forecasting, free cash flow modeling, and translating financial performance into valuation outcomes.
